<annotation>
	<folder>100</folder>
	<filename>69.png</filename>
	<path>C:\Users\user\Desktop\pentacore\NEWIMG\100\69.png</path>
	<source>
		<database>Unknown</database>
	</source>
	<size>
		<width>512</width>
		<height>512</height>
		<depth>3</depth>
	</size>
	<segmented>0</segmented>
	<object>
		<name>MOTHERBOARD</name>
		<pose>Unspecified</pose>
		<truncated>0</truncated>
		<difficult>0</difficult>
		<bndbox>
			<xmin>102</xmin>
			<ymin>49</ymin>
			<xmax>403</xmax>
			<ymax>437</ymax>
		</bndbox>
	</object>
	<object>
		<name>CPU</name>
		<pose>Unspecified</pose>
		<truncated>0</truncated>
		<difficult>0</difficult>
		<bndbox>
			<xmin>257</xmin>
			<ymin>211</ymin>
			<xmax>347</xmax>
			<ymax>293</ymax>
		</bndbox>
	</object>
	<object>
		<name>RAM</name>
		<pose>Unspecified</pose>
		<truncated>0</truncated>
		<difficult>0</difficult>
		<bndbox>
			<xmin>223</xmin>
			<ymin>328</ymin>
			<xmax>398</xmax>
			<ymax>398</ymax>
		</bndbox>
	</object>
	<object>
		<name>GPU</name>
		<pose>Unspecified</pose>
		<truncated>0</truncated>
		<difficult>0</difficult>
		<bndbox>
			<xmin>201</xmin>
			<ymin>129</ymin>
			<xmax>219</xmax>
			<ymax>295</ymax>
		</bndbox>
	</object>
	<object>
		<name>GPU</name>
		<pose>Unspecified</pose>
		<truncated>0</truncated>
		<difficult>0</difficult>
		<bndbox>
			<xmin>128</xmin>
			<ymin>126</ymin>
			<xmax>147</xmax>
			<ymax>292</ymax>
		</bndbox>
	</object>
	<object>
		<name>SSD</name>
		<pose>Unspecified</pose>
		<truncated>0</truncated>
		<difficult>0</difficult>
		<bndbox>
			<xmin>143</xmin>
			<ymin>219</ymin>
			<xmax>174</xmax>
			<ymax>235</ymax>
		</bndbox>
	</object>
	<object>
		<name>SSD</name>
		<pose>Unspecified</pose>
		<truncated>0</truncated>
		<difficult>0</difficult>
		<bndbox>
			<xmin>169</xmin>
			<ymin>271</ymin>
			<xmax>198</xmax>
			<ymax>290</ymax>
		</bndbox>
	</object>
</annotation>
