<annotation>
	<folder>300</folder>
	<filename>222.png</filename>
	<path>C:\Users\user\Desktop\pentaport\project\NEWIMG\300\222.png</path>
	<source>
		<database>Unknown</database>
	</source>
	<size>
		<width>512</width>
		<height>512</height>
		<depth>3</depth>
	</size>
	<segmented>0</segmented>
	<object>
		<name>CPU</name>
		<pose>Unspecified</pose>
		<truncated>0</truncated>
		<difficult>0</difficult>
		<bndbox>
			<xmin>174</xmin>
			<ymin>157</ymin>
			<xmax>250</xmax>
			<ymax>235</ymax>
		</bndbox>
	</object>
	<object>
		<name>RAM</name>
		<pose>Unspecified</pose>
		<truncated>0</truncated>
		<difficult>0</difficult>
		<bndbox>
			<xmin>184</xmin>
			<ymin>68</ymin>
			<xmax>308</xmax>
			<ymax>205</ymax>
		</bndbox>
	</object>
	<object>
		<name>GPU</name>
		<pose>Unspecified</pose>
		<truncated>0</truncated>
		<difficult>0</difficult>
		<bndbox>
			<xmin>237</xmin>
			<ymin>251</ymin>
			<xmax>299</xmax>
			<ymax>345</ymax>
		</bndbox>
	</object>
	<object>
		<name>GPU</name>
		<pose>Unspecified</pose>
		<truncated>0</truncated>
		<difficult>0</difficult>
		<bndbox>
			<xmin>291</xmin>
			<ymin>278</ymin>
			<xmax>357</xmax>
			<ymax>406</ymax>
		</bndbox>
	</object>
	<object>
		<name>SSD</name>
		<pose>Unspecified</pose>
		<truncated>0</truncated>
		<difficult>0</difficult>
		<bndbox>
			<xmin>274</xmin>
			<ymin>212</ymin>
			<xmax>298</xmax>
			<ymax>239</ymax>
		</bndbox>
	</object>
	<object>
		<name>MOTHERBOARD</name>
		<pose>Unspecified</pose>
		<truncated>0</truncated>
		<difficult>0</difficult>
		<bndbox>
			<xmin>69</xmin>
			<ymin>60</ymin>
			<xmax>436</xmax>
			<ymax>508</ymax>
		</bndbox>
	</object>
</annotation>
